{
  "strategy_name": "FractalAggressiveV14",
  "params": {
    "roi": {
      "0": 0.3,
      "60": 0.1,
      "150": 0.03,
      "300": 0
    },
    "stoploss": {
      "stoploss": -0.1
    },
    "trailing": {
      "trailing_stop": true,
      "trailing_stop_positive": 0.03,
      "trailing_stop_positive_offset": 0.05,
      "trailing_only_offset_is_reached": true
    },
    "max_open_trades": {
      "max_open_trades": 3
    },
    "buy": {
      "b1_adx": 29,
      "b1_obv": 1.027,
      "b1_rsi": 60,
      "b2_adx": 33,
      "b2_obv": 1.472,
      "b2_rsi": 74,
      "b3_adx": 41,
      "b3_obv": 1.047,
      "b3_rsi": 50,
      "btc_adx_threshold": 45,
      "btc_rsi_threshold": 71
    }
  },
  "ft_stratparam_v": 1,
  "export_time": "2026-01-18 09:42:43.145668+00:00"
}